; ModuleID = './MultiSource.Applications.lua/24.lopcodes.bc'
target datalayout = "e-m:e-i64:64-f80:128-n8:16:32:64-S128"
target triple = "x86_64-unknown-linux-gnu"

@.str = private unnamed_addr constant [5 x i8] c"MOVE\00", align 1
@.str.1 = private unnamed_addr constant [6 x i8] c"LOADK\00", align 1
@.str.2 = private unnamed_addr constant [9 x i8] c"LOADBOOL\00", align 1
@.str.3 = private unnamed_addr constant [8 x i8] c"LOADNIL\00", align 1
@.str.4 = private unnamed_addr constant [9 x i8] c"GETUPVAL\00", align 1
@.str.5 = private unnamed_addr constant [10 x i8] c"GETGLOBAL\00", align 1
@.str.6 = private unnamed_addr constant [9 x i8] c"GETTABLE\00", align 1
@.str.7 = private unnamed_addr constant [10 x i8] c"SETGLOBAL\00", align 1
@.str.8 = private unnamed_addr constant [9 x i8] c"SETUPVAL\00", align 1
@.str.9 = private unnamed_addr constant [9 x i8] c"SETTABLE\00", align 1
@.str.10 = private unnamed_addr constant [9 x i8] c"NEWTABLE\00", align 1
@.str.11 = private unnamed_addr constant [5 x i8] c"SELF\00", align 1
@.str.12 = private unnamed_addr constant [4 x i8] c"ADD\00", align 1
@.str.13 = private unnamed_addr constant [4 x i8] c"SUB\00", align 1
@.str.14 = private unnamed_addr constant [4 x i8] c"MUL\00", align 1
@.str.15 = private unnamed_addr constant [4 x i8] c"DIV\00", align 1
@.str.16 = private unnamed_addr constant [4 x i8] c"MOD\00", align 1
@.str.17 = private unnamed_addr constant [4 x i8] c"POW\00", align 1
@.str.18 = private unnamed_addr constant [4 x i8] c"UNM\00", align 1
@.str.19 = private unnamed_addr constant [4 x i8] c"NOT\00", align 1
@.str.20 = private unnamed_addr constant [4 x i8] c"LEN\00", align 1
@.str.21 = private unnamed_addr constant [7 x i8] c"CONCAT\00", align 1
@.str.22 = private unnamed_addr constant [4 x i8] c"JMP\00", align 1
@.str.23 = private unnamed_addr constant [3 x i8] c"EQ\00", align 1
@.str.24 = private unnamed_addr constant [3 x i8] c"LT\00", align 1
@.str.25 = private unnamed_addr constant [3 x i8] c"LE\00", align 1
@.str.26 = private unnamed_addr constant [5 x i8] c"TEST\00", align 1
@.str.27 = private unnamed_addr constant [8 x i8] c"TESTSET\00", align 1
@.str.28 = private unnamed_addr constant [5 x i8] c"CALL\00", align 1
@.str.29 = private unnamed_addr constant [9 x i8] c"TAILCALL\00", align 1
@.str.30 = private unnamed_addr constant [7 x i8] c"RETURN\00", align 1
@.str.31 = private unnamed_addr constant [8 x i8] c"FORLOOP\00", align 1
@.str.32 = private unnamed_addr constant [8 x i8] c"FORPREP\00", align 1
@.str.33 = private unnamed_addr constant [9 x i8] c"TFORLOOP\00", align 1
@.str.34 = private unnamed_addr constant [8 x i8] c"SETLIST\00", align 1
@.str.35 = private unnamed_addr constant [6 x i8] c"CLOSE\00", align 1
@.str.36 = private unnamed_addr constant [8 x i8] c"CLOSURE\00", align 1
@.str.37 = private unnamed_addr constant [7 x i8] c"VARARG\00", align 1
@luaP_opnames = hidden constant [39 x i8*] [i8* getelementptr inbounds ([5 x i8], [5 x i8]* @.str, i32 0, i32 0), i8* getelementptr inbounds ([6 x i8], [6 x i8]* @.str.1, i32 0, i32 0), i8* getelementptr inbounds ([9 x i8], [9 x i8]* @.str.2, i32 0, i32 0), i8* getelementptr inbounds ([8 x i8], [8 x i8]* @.str.3, i32 0, i32 0), i8* getelementptr inbounds ([9 x i8], [9 x i8]* @.str.4, i32 0, i32 0), i8* getelementptr inbounds ([10 x i8], [10 x i8]* @.str.5, i32 0, i32 0), i8* getelementptr inbounds ([9 x i8], [9 x i8]* @.str.6, i32 0, i32 0), i8* getelementptr inbounds ([10 x i8], [10 x i8]* @.str.7, i32 0, i32 0), i8* getelementptr inbounds ([9 x i8], [9 x i8]* @.str.8, i32 0, i32 0), i8* getelementptr inbounds ([9 x i8], [9 x i8]* @.str.9, i32 0, i32 0), i8* getelementptr inbounds ([9 x i8], [9 x i8]* @.str.10, i32 0, i32 0), i8* getelementptr inbounds ([5 x i8], [5 x i8]* @.str.11, i32 0, i32 0), i8* getelementptr inbounds ([4 x i8], [4 x i8]* @.str.12, i32 0, i32 0), i8* getelementptr inbounds ([4 x i8], [4 x i8]* @.str.13, i32 0, i32 0), i8* getelementptr inbounds ([4 x i8], [4 x i8]* @.str.14, i32 0, i32 0), i8* getelementptr inbounds ([4 x i8], [4 x i8]* @.str.15, i32 0, i32 0), i8* getelementptr inbounds ([4 x i8], [4 x i8]* @.str.16, i32 0, i32 0), i8* getelementptr inbounds ([4 x i8], [4 x i8]* @.str.17, i32 0, i32 0), i8* getelementptr inbounds ([4 x i8], [4 x i8]* @.str.18, i32 0, i32 0), i8* getelementptr inbounds ([4 x i8], [4 x i8]* @.str.19, i32 0, i32 0), i8* getelementptr inbounds ([4 x i8], [4 x i8]* @.str.20, i32 0, i32 0), i8* getelementptr inbounds ([7 x i8], [7 x i8]* @.str.21, i32 0, i32 0), i8* getelementptr inbounds ([4 x i8], [4 x i8]* @.str.22, i32 0, i32 0), i8* getelementptr inbounds ([3 x i8], [3 x i8]* @.str.23, i32 0, i32 0), i8* getelementptr inbounds ([3 x i8], [3 x i8]* @.str.24, i32 0, i32 0), i8* getelementptr inbounds ([3 x i8], [3 x i8]* @.str.25, i32 0, i32 0), i8* getelementptr inbounds ([5 x i8], [5 x i8]* @.str.26, i32 0, i32 0), i8* getelementptr inbounds ([8 x i8], [8 x i8]* @.str.27, i32 0, i32 0), i8* getelementptr inbounds ([5 x i8], [5 x i8]* @.str.28, i32 0, i32 0), i8* getelementptr inbounds ([9 x i8], [9 x i8]* @.str.29, i32 0, i32 0), i8* getelementptr inbounds ([7 x i8], [7 x i8]* @.str.30, i32 0, i32 0), i8* getelementptr inbounds ([8 x i8], [8 x i8]* @.str.31, i32 0, i32 0), i8* getelementptr inbounds ([8 x i8], [8 x i8]* @.str.32, i32 0, i32 0), i8* getelementptr inbounds ([9 x i8], [9 x i8]* @.str.33, i32 0, i32 0), i8* getelementptr inbounds ([8 x i8], [8 x i8]* @.str.34, i32 0, i32 0), i8* getelementptr inbounds ([6 x i8], [6 x i8]* @.str.35, i32 0, i32 0), i8* getelementptr inbounds ([8 x i8], [8 x i8]* @.str.36, i32 0, i32 0), i8* getelementptr inbounds ([7 x i8], [7 x i8]* @.str.37, i32 0, i32 0), i8* null], align 16
@luaP_opmodes = hidden constant [38 x i8] c"`qT`Pql1\10<Tl||||||```h\22\BC\BC\BC\E4\E4TT\10bb\84\14\00QP", align 16

!llvm.ident = !{!0}

!0 = !{!"clang version 3.7.0 (tags/RELEASE_370/final)"}
